GalDynPsr/ExcessZ.py
GalDynPsr/Excesspl.py
GalDynPsr/GC_harris.txt
GalDynPsr/README.txt
GalDynPsr/ReadGC.py
GalDynPsr/Shk.py
GalDynPsr/__init__.py
GalDynPsr/err_HFhigh.py
GalDynPsr/err_HFlow.py
GalDynPsr/err_NT.py
GalDynPsr/err_Shklovskii.py
GalDynPsr/err_excesspl_Damour.py
GalDynPsr/err_excesspl_Reid.py
GalDynPsr/galpyMWBHRfo.py
GalDynPsr/galpyMWBHZfo.py
GalDynPsr/galpyMWBHpl.py
GalDynPsr/galpyMWRfo.py
GalDynPsr/galpyMWZfo.py
GalDynPsr/galpyMWpl.py
GalDynPsr/modelA.py
GalDynPsr/modelB.py
GalDynPsr/modelC.py
GalDynPsr/modelD.py
GalDynPsr/modelEa.py
GalDynPsr/modelEb.py
GalDynPsr/modelFa.py
GalDynPsr/modelFb.py
GalDynPsr/modelGa.py
GalDynPsr/modelGb.py
GalDynPsr/modelHa.py
GalDynPsr/modelHb.py
GalDynPsr/modelIa.py
GalDynPsr/modelIb.py
GalDynPsr/modelJa.py
GalDynPsr/modelJb.py
GalDynPsr/modelKa.py
GalDynPsr/modelKb.py
GalDynPsr/modelLa.py
GalDynPsr/modelLb.py
GalDynPsr/parameters.in
GalDynPsr/pdotint.py
GalDynPsr/read_parameters.py
GalDynPsr-1.0.0.dist-info/METADATA
GalDynPsr-1.0.0.dist-info/RECORD
GalDynPsr-1.0.0.dist-info/WHEEL
GalDynPsr-1.0.0.dist-info/top_level.txt
