Metadata-Version: 2.1
Name: GalDynPsr
Version: 1.0.0
Summary: A practise package
Home-page: https://github.com/pathakdhruv/GalDynPsr
Author: Dhruv Pathak
Author-email: pathakdhruv9786@gmail.com
License: New BSD
Platform: UNKNOWN
Classifier: Programming Language :: Python :: 3
Classifier: License :: OSI Approved :: BSD License
Classifier: Operating System :: OS Independent
